{
    "5b39f34c-85f3-31b4-5eda-6b84d94eb3a8": {
        "paletteKey": "FlexLayoutRow",
        "commentid": null,
        "designerReference": [
            {
                "_key": "componentLabel",
                "_value": "Row",
                "_type": "kv",
                "_attrDef": "p",
                "_useAsLabel": true
            },
            {
                "_key": "style",
                "_value": "",
                "_type": "kv",
                "_attrDef": "p"
            },
            {
                "_key": "class",
                "_value": [
                    "marginbottom1em",
                    "marginTop2em",
                    "fullWidth"
                ],
                "_type": "dav",
                "_attrDef": "p"
            },
            {
                "_key": "fxFlex",
                "_value": "",
                "_type": "kv",
                "_attrDef": "p"
            },
            {
                "_key": "fxLayoutGap",
                "_value": "",
                "_type": "kv",
                "_attrDef": "p"
            },
            {
                "_key": "wrap",
                "_value": "wrap",
                "_type": "a",
                "_attrDef": "p"
            },
            {
                "_key": "layoutAlign",
                "_value": "center",
                "_type": "a",
                "_attrDef": "p"
            },
            {
                "_key": "pLayoutAlign",
                "_value": "center",
                "_type": "a",
                "_attrDef": "p"
            },
            {
                "_key": "[fxShow]",
                "_value": "true",
                "_type": "kv",
                "_attrDef": "p"
            }
        ],
        "d7ade8fd-a1ff-6320-03a5-698514195a98": {
            "paletteKey": "FlexLayoutCol",
            "parentEditorKey": "5b39f34c-85f3-31b4-5eda-6b84d94eb3a8",
            "commentid": null,
            "designerReference": [
                {
                    "_key": "componentLabel",
                    "_value": "Column",
                    "_type": "kv",
                    "_attrDef": "p",
                    "_useAsLabel": true
                },
                {
                    "_key": "style",
                    "_value": "position:relative;",
                    "_type": "kv",
                    "_attrDef": "p"
                },
                {
                    "_key": "class",
                    "_value": [
                        "background"
                    ],
                    "_type": "dav",
                    "_attrDef": "p"
                },
                {
                    "_key": "fxFlex",
                    "_value": "",
                    "_type": "kv",
                    "_attrDef": "p"
                },
                {
                    "_key": "fxLayoutGap",
                    "_value": "",
                    "_type": "kv",
                    "_attrDef": "p"
                },
                {
                    "_key": "wrap",
                    "_value": "wrap",
                    "_type": "a",
                    "_attrDef": "p"
                },
                {
                    "_key": "layoutAlign",
                    "_value": "start",
                    "_type": "a",
                    "_attrDef": "p"
                },
                {
                    "_key": "pLayoutAlign",
                    "_value": "stretch",
                    "_type": "a",
                    "_attrDef": "p"
                },
                {
                    "_key": "[fxShow]",
                    "_value": "true",
                    "_type": "kv",
                    "_attrDef": "p"
                }
            ],
            "65a03f3a-862f-c3e3-b9e4-3361e2c758df": {
                "paletteKey": "FlexLayoutCol",
                "parentEditorKey": "d7ade8fd-a1ff-6320-03a5-698514195a98",
                "isCommented": "true",
                "commentid": "1658410966692",
                "designerReference": [
                    {
                        "_key": "componentLabel",
                        "_value": "line",
                        "_type": "kv",
                        "_attrDef": "p",
                        "_useAsLabel": true
                    },
                    {
                        "_key": "style",
                        "_value": "position:absolute;width:350px",
                        "_type": "kv",
                        "_attrDef": "p"
                    },
                    {
                        "_key": "class",
                        "_value": [
                            "yellowlines"
                        ],
                        "_type": "dav",
                        "_attrDef": "p"
                    },
                    {
                        "_key": "fxFlex",
                        "_value": "",
                        "_type": "kv",
                        "_attrDef": "p"
                    },
                    {
                        "_key": "fxLayoutGap",
                        "_value": "",
                        "_type": "kv",
                        "_attrDef": "p"
                    },
                    {
                        "_key": "wrap",
                        "_value": "wrap",
                        "_type": "a",
                        "_attrDef": "p"
                    },
                    {
                        "_key": "layoutAlign",
                        "_value": "start",
                        "_type": "a",
                        "_attrDef": "p"
                    },
                    {
                        "_key": "pLayoutAlign",
                        "_value": "stretch",
                        "_type": "a",
                        "_attrDef": "p"
                    },
                    {
                        "_key": "[fxShow]",
                        "_value": "true",
                        "_type": "kv",
                        "_attrDef": "p"
                    }
                ]
            },
            "45b5b8fb-2200-7eca-4041-7dd78ff616c5": {
                "paletteKey": "FlexLayoutRow",
                "parentEditorKey": "d7ade8fd-a1ff-6320-03a5-698514195a98",
                "commentid": null,
                "designerReference": [
                    {
                        "_key": "componentLabel",
                        "_value": "Row",
                        "_type": "kv",
                        "_attrDef": "p",
                        "_useAsLabel": true
                    },
                    {
                        "_key": "style",
                        "_value": "",
                        "_type": "kv",
                        "_attrDef": "p"
                    },
                    {
                        "_key": "class",
                        "_value": [
                            "whiteText"
                        ],
                        "_type": "dav",
                        "_attrDef": "p"
                    },
                    {
                        "_key": "fxFlex",
                        "_value": "",
                        "_type": "kv",
                        "_attrDef": "p"
                    },
                    {
                        "_key": "fxLayoutGap",
                        "_value": "",
                        "_type": "kv",
                        "_attrDef": "p"
                    },
                    {
                        "_key": "wrap",
                        "_value": "wrap",
                        "_type": "a",
                        "_attrDef": "p"
                    },
                    {
                        "_key": "layoutAlign",
                        "_value": "center",
                        "_type": "a",
                        "_attrDef": "p"
                    },
                    {
                        "_key": "pLayoutAlign",
                        "_value": "center",
                        "_type": "a",
                        "_attrDef": "p"
                    },
                    {
                        "_key": "[fxShow]",
                        "_value": "true",
                        "_type": "kv",
                        "_attrDef": "p"
                    }
                ],
                "638be213-fa8d-92a6-61f3-66dfc47401d2": {
                    "paletteKey": "FlexLayoutCol",
                    "parentEditorKey": "45b5b8fb-2200-7eca-4041-7dd78ff616c5",
                    "commentid": null,
                    "designerReference": [
                        {
                            "_key": "componentLabel",
                            "_value": "Column",
                            "_type": "kv",
                            "_attrDef": "p",
                            "_useAsLabel": true
                        },
                        {
                            "_key": "style",
                            "_value": "",
                            "_type": "kv",
                            "_attrDef": "p"
                        },
                        {
                            "_key": "class",
                            "_value": [],
                            "_type": "dav",
                            "_attrDef": "p"
                        },
                        {
                            "_key": "fxFlex",
                            "_value": "",
                            "_type": "kv",
                            "_attrDef": "p"
                        },
                        {
                            "_key": "fxLayoutGap",
                            "_value": "",
                            "_type": "kv",
                            "_attrDef": "p"
                        },
                        {
                            "_key": "wrap",
                            "_value": "wrap",
                            "_type": "a",
                            "_attrDef": "p"
                        },
                        {
                            "_key": "layoutAlign",
                            "_value": "center",
                            "_type": "a",
                            "_attrDef": "p"
                        },
                        {
                            "_key": "pLayoutAlign",
                            "_value": "center",
                            "_type": "a",
                            "_attrDef": "p"
                        },
                        {
                            "_key": "[fxShow]",
                            "_value": "true",
                            "_type": "kv",
                            "_attrDef": "p"
                        }
                    ],
                    "c5b68caa-afa9-b0be-9380-9f80b7672f5d": {
                        "paletteKey": "Html5",
                        "parentEditorKey": "638be213-fa8d-92a6-61f3-66dfc47401d2",
                        "isAdvancedComponent": true,
                        "commentid": null,
                        "designerReference": [
                            {
                                "_key": "style",
                                "_value": "",
                                "_type": "kv",
                                "_attrDef": "p"
                            },
                            {
                                "_key": "class",
                                "_value": [
                                    "marginbottom",
                                    "fontSize4em"
                                ],
                                "_type": "dav",
                                "_attrDef": "p"
                            },
                            {
                                "_key": "htmlElement",
                                "_value": "p",
                                "_type": "dav",
                                "_attrDef": "p",
                                "_useAsLabel": true
                            },
                            {
                                "_key": "tagType",
                                "_value": "p",
                                "_type": "a",
                                "_attrDef": "p",
                                "_visibility": false
                            },
                            {
                                "_key": "name",
                                "_value": "",
                                "_type": "kv",
                                "_attrDef": "p",
                                "_visibility": false
                            },
                            {
                                "_key": "sandbox",
                                "_value": "",
                                "_type": "kv",
                                "_attrDef": "p",
                                "_visibility": false
                            },
                            {
                                "_key": "src",
                                "_value": "",
                                "_type": "kv",
                                "_attrDef": "p",
                                "_visibility": false
                            },
                            {
                                "_key": "srcdoc",
                                "_value": "",
                                "_type": "kv",
                                "_attrDef": "p",
                                "_visibility": false
                            },
                            {
                                "_key": "width",
                                "_value": "",
                                "_type": "kv",
                                "_attrDef": "p",
                                "_visibility": false
                            },
                            {
                                "_key": "[autoplay]",
                                "_value": "",
                                "_type": "kv",
                                "_attrDef": "p",
                                "_visibility": false
                            },
                            {
                                "_key": "[loop]",
                                "_value": "",
                                "_type": "kv",
                                "_attrDef": "p",
                                "_visibility": false
                            },
                            {
                                "_key": "data",
                                "_value": "",
                                "_type": "kv",
                                "_attrDef": "p",
                                "_visibility": false
                            },
                            {
                                "_key": "audioSource",
                                "_value": [],
                                "_type": "a",
                                "_attrDef": "p",
                                "_visibility": false
                            },
                            {
                                "_key": "videoSource",
                                "_value": [],
                                "_type": "a",
                                "_attrDef": "p",
                                "_visibility": false
                            },
                            {
                                "_key": "audioDatasource",
                                "_value": "",
                                "_type": "a",
                                "_attrDef": "p",
                                "_visibility": false
                            },
                            {
                                "_key": "audioSrc",
                                "_value": "",
                                "_type": "a",
                                "_attrDef": "p",
                                "_visibility": false
                            },
                            {
                                "_key": "audioType",
                                "_value": "",
                                "_type": "a",
                                "_attrDef": "p",
                                "_visibility": false
                            },
                            {
                                "_key": "videoDatasource",
                                "_value": "",
                                "_type": "a",
                                "_attrDef": "p",
                                "_visibility": false
                            },
                            {
                                "_key": "videoSrc",
                                "_value": "",
                                "_type": "a",
                                "_attrDef": "p",
                                "_visibility": false
                            },
                            {
                                "_key": "videoType",
                                "_value": "",
                                "_type": "a",
                                "_attrDef": "p",
                                "_visibility": false
                            },
                            {
                                "_key": "(audioplay)",
                                "_value": "",
                                "_type": "a",
                                "_attrDef": "p",
                                "_visibility": false
                            },
                            {
                                "_key": "(videoplay)",
                                "_value": "",
                                "_type": "a",
                                "_attrDef": "p",
                                "_visibility": false
                            },
                            {
                                "_key": "(audiopause)",
                                "_value": "",
                                "_type": "kv",
                                "_attrDef": "p",
                                "_visibility": false
                            },
                            {
                                "_key": "(videopause)",
                                "_value": "",
                                "_type": "kv",
                                "_attrDef": "p",
                                "_visibility": false
                            },
                            {
                                "_key": "(audioended)",
                                "_value": "",
                                "_type": "kv",
                                "_attrDef": "p",
                                "_visibility": false
                            },
                            {
                                "_key": "(videoended)",
                                "_value": "",
                                "_type": "kv",
                                "_attrDef": "p",
                                "_visibility": false
                            }
                        ],
                        "bcc05d95-ac4a-cebe-d673-a12a9587e61c": {
                            "paletteKey": "html-editor",
                            "parentEditorKey": "c5b68caa-afa9-b0be-9380-9f80b7672f5d",
                            "isAdvancedChildComponent": true,
                            "commentid": null,
                            "designerReference": [
                                {
                                    "_key": "style",
                                    "_value": "",
                                    "_type": "kv",
                                    "_attrDef": "p"
                                },
                                {
                                    "_key": "class",
                                    "_value": "",
                                    "_type": "dav",
                                    "_attrDef": "p"
                                },
                                {
                                    "_key": "html",
                                    "_value": "Art Gallery App",
                                    "_type": "a",
                                    "_attrDef": "p"
                                }
                            ]
                        }
                    },
                    "1ba22cd8-759b-d4ed-b081-872593185057": {
                        "paletteKey": "Html5",
                        "parentEditorKey": "638be213-fa8d-92a6-61f3-66dfc47401d2",
                        "isAdvancedComponent": true,
                        "commentid": null,
                        "designerReference": [
                            {
                                "_key": "style",
                                "_value": "",
                                "_type": "kv",
                                "_attrDef": "p"
                            },
                            {
                                "_key": "class",
                                "_value": [
                                    "centerText",
                                    "width80",
                                    "whiteText"
                                ],
                                "_type": "dav",
                                "_attrDef": "p"
                            },
                            {
                                "_key": "htmlElement",
                                "_value": "p",
                                "_type": "dav",
                                "_attrDef": "p",
                                "_useAsLabel": true
                            },
                            {
                                "_key": "tagType",
                                "_value": "p",
                                "_type": "a",
                                "_attrDef": "p",
                                "_visibility": false
                            },
                            {
                                "_key": "name",
                                "_value": "",
                                "_type": "kv",
                                "_attrDef": "p",
                                "_visibility": false
                            },
                            {
                                "_key": "sandbox",
                                "_value": "",
                                "_type": "kv",
                                "_attrDef": "p",
                                "_visibility": false
                            },
                            {
                                "_key": "src",
                                "_value": "",
                                "_type": "kv",
                                "_attrDef": "p",
                                "_visibility": false
                            },
                            {
                                "_key": "srcdoc",
                                "_value": "",
                                "_type": "kv",
                                "_attrDef": "p",
                                "_visibility": false
                            },
                            {
                                "_key": "width",
                                "_value": "",
                                "_type": "kv",
                                "_attrDef": "p",
                                "_visibility": false
                            },
                            {
                                "_key": "[autoplay]",
                                "_value": "",
                                "_type": "kv",
                                "_attrDef": "p",
                                "_visibility": false
                            },
                            {
                                "_key": "[loop]",
                                "_value": "",
                                "_type": "kv",
                                "_attrDef": "p",
                                "_visibility": false
                            },
                            {
                                "_key": "data",
                                "_value": "",
                                "_type": "kv",
                                "_attrDef": "p",
                                "_visibility": false
                            },
                            {
                                "_key": "audioSource",
                                "_value": [],
                                "_type": "a",
                                "_attrDef": "p",
                                "_visibility": false
                            },
                            {
                                "_key": "videoSource",
                                "_value": [],
                                "_type": "a",
                                "_attrDef": "p",
                                "_visibility": false
                            },
                            {
                                "_key": "audioDatasource",
                                "_value": "",
                                "_type": "a",
                                "_attrDef": "p",
                                "_visibility": false
                            },
                            {
                                "_key": "audioSrc",
                                "_value": "",
                                "_type": "a",
                                "_attrDef": "p",
                                "_visibility": false
                            },
                            {
                                "_key": "audioType",
                                "_value": "",
                                "_type": "a",
                                "_attrDef": "p",
                                "_visibility": false
                            },
                            {
                                "_key": "videoDatasource",
                                "_value": "",
                                "_type": "a",
                                "_attrDef": "p",
                                "_visibility": false
                            },
                            {
                                "_key": "videoSrc",
                                "_value": "",
                                "_type": "a",
                                "_attrDef": "p",
                                "_visibility": false
                            },
                            {
                                "_key": "videoType",
                                "_value": "",
                                "_type": "a",
                                "_attrDef": "p",
                                "_visibility": false
                            },
                            {
                                "_key": "(audioplay)",
                                "_value": "",
                                "_type": "a",
                                "_attrDef": "p",
                                "_visibility": false
                            },
                            {
                                "_key": "(videoplay)",
                                "_value": "",
                                "_type": "a",
                                "_attrDef": "p",
                                "_visibility": false
                            },
                            {
                                "_key": "(audiopause)",
                                "_value": "",
                                "_type": "kv",
                                "_attrDef": "p",
                                "_visibility": false
                            },
                            {
                                "_key": "(videopause)",
                                "_value": "",
                                "_type": "kv",
                                "_attrDef": "p",
                                "_visibility": false
                            },
                            {
                                "_key": "(audioended)",
                                "_value": "",
                                "_type": "kv",
                                "_attrDef": "p",
                                "_visibility": false
                            },
                            {
                                "_key": "(videoended)",
                                "_value": "",
                                "_type": "kv",
                                "_attrDef": "p",
                                "_visibility": false
                            }
                        ],
                        "e2270507-a419-1ead-6cd4-6d69017b03c6": {
                            "paletteKey": "html-editor",
                            "parentEditorKey": "1ba22cd8-759b-d4ed-b081-872593185057",
                            "isAdvancedChildComponent": true,
                            "commentid": null,
                            "designerReference": [
                                {
                                    "_key": "style",
                                    "_value": "",
                                    "_type": "kv",
                                    "_attrDef": "p"
                                },
                                {
                                    "_key": "class",
                                    "_value": "",
                                    "_type": "dav",
                                    "_attrDef": "p"
                                },
                                {
                                    "_key": "html",
                                    "_value": "Browse original paintings, fine art and photographs from talented artists around the world. An art Gallary application for art lovers, that showcases the art that we currently have in our gallary and its story.",
                                    "_type": "a",
                                    "_attrDef": "p"
                                }
                            ]
                        }
                    },
                    "1ad10f38-6718-f596-2d23-18bc6ae2581a": {
                        "paletteKey": "Html5",
                        "parentEditorKey": "638be213-fa8d-92a6-61f3-66dfc47401d2",
                        "isAdvancedComponent": true,
                        "commentid": null,
                        "designerReference": [
                            {
                                "_key": "style",
                                "_value": "",
                                "_type": "kv",
                                "_attrDef": "p"
                            },
                            {
                                "_key": "class",
                                "_value": [
                                    "whiteText"
                                ],
                                "_type": "dav",
                                "_attrDef": "p"
                            },
                            {
                                "_key": "htmlElement",
                                "_value": "p",
                                "_type": "dav",
                                "_attrDef": "p",
                                "_useAsLabel": true
                            },
                            {
                                "_key": "tagType",
                                "_value": "p",
                                "_type": "a",
                                "_attrDef": "p",
                                "_visibility": false
                            },
                            {
                                "_key": "name",
                                "_value": "",
                                "_type": "kv",
                                "_attrDef": "p",
                                "_visibility": false
                            },
                            {
                                "_key": "sandbox",
                                "_value": "",
                                "_type": "kv",
                                "_attrDef": "p",
                                "_visibility": false
                            },
                            {
                                "_key": "src",
                                "_value": "",
                                "_type": "kv",
                                "_attrDef": "p",
                                "_visibility": false
                            },
                            {
                                "_key": "srcdoc",
                                "_value": "",
                                "_type": "kv",
                                "_attrDef": "p",
                                "_visibility": false
                            },
                            {
                                "_key": "width",
                                "_value": "",
                                "_type": "kv",
                                "_attrDef": "p",
                                "_visibility": false
                            },
                            {
                                "_key": "[autoplay]",
                                "_value": "",
                                "_type": "kv",
                                "_attrDef": "p",
                                "_visibility": false
                            },
                            {
                                "_key": "[loop]",
                                "_value": "",
                                "_type": "kv",
                                "_attrDef": "p",
                                "_visibility": false
                            },
                            {
                                "_key": "data",
                                "_value": "",
                                "_type": "kv",
                                "_attrDef": "p",
                                "_visibility": false
                            },
                            {
                                "_key": "audioSource",
                                "_value": [],
                                "_type": "a",
                                "_attrDef": "p",
                                "_visibility": false
                            },
                            {
                                "_key": "videoSource",
                                "_value": [],
                                "_type": "a",
                                "_attrDef": "p",
                                "_visibility": false
                            },
                            {
                                "_key": "audioDatasource",
                                "_value": "",
                                "_type": "a",
                                "_attrDef": "p",
                                "_visibility": false
                            },
                            {
                                "_key": "audioSrc",
                                "_value": "",
                                "_type": "a",
                                "_attrDef": "p",
                                "_visibility": false
                            },
                            {
                                "_key": "audioType",
                                "_value": "",
                                "_type": "a",
                                "_attrDef": "p",
                                "_visibility": false
                            },
                            {
                                "_key": "videoDatasource",
                                "_value": "",
                                "_type": "a",
                                "_attrDef": "p",
                                "_visibility": false
                            },
                            {
                                "_key": "videoSrc",
                                "_value": "",
                                "_type": "a",
                                "_attrDef": "p",
                                "_visibility": false
                            },
                            {
                                "_key": "videoType",
                                "_value": "",
                                "_type": "a",
                                "_attrDef": "p",
                                "_visibility": false
                            },
                            {
                                "_key": "(audioplay)",
                                "_value": "",
                                "_type": "a",
                                "_attrDef": "p",
                                "_visibility": false
                            },
                            {
                                "_key": "(videoplay)",
                                "_value": "",
                                "_type": "a",
                                "_attrDef": "p",
                                "_visibility": false
                            },
                            {
                                "_key": "(audiopause)",
                                "_value": "",
                                "_type": "kv",
                                "_attrDef": "p",
                                "_visibility": false
                            },
                            {
                                "_key": "(videopause)",
                                "_value": "",
                                "_type": "kv",
                                "_attrDef": "p",
                                "_visibility": false
                            },
                            {
                                "_key": "(audioended)",
                                "_value": "",
                                "_type": "kv",
                                "_attrDef": "p",
                                "_visibility": false
                            },
                            {
                                "_key": "(videoended)",
                                "_value": "",
                                "_type": "kv",
                                "_attrDef": "p",
                                "_visibility": false
                            }
                        ],
                        "e1961bc2-b0da-00b4-3be0-be278766f4f1": {
                            "paletteKey": "html-editor",
                            "parentEditorKey": "1ad10f38-6718-f596-2d23-18bc6ae2581a",
                            "isAdvancedChildComponent": true,
                            "commentid": null,
                            "designerReference": [
                                {
                                    "_key": "style",
                                    "_value": "",
                                    "_type": "kv",
                                    "_attrDef": "p"
                                },
                                {
                                    "_key": "class",
                                    "_value": "",
                                    "_type": "dav",
                                    "_attrDef": "p"
                                },
                                {
                                    "_key": "html",
                                    "_value": "",
                                    "_type": "a",
                                    "_attrDef": "p"
                                }
                            ]
                        }
                    },
                    "c5b016dc-adfe-e1f0-763d-9498594b000a": {
                        "paletteKey": "FlexLayoutRow",
                        "parentEditorKey": "638be213-fa8d-92a6-61f3-66dfc47401d2",
                        "commentid": null,
                        "designerReference": [
                            {
                                "_key": "componentLabel",
                                "_value": "Row",
                                "_type": "kv",
                                "_attrDef": "p",
                                "_useAsLabel": true
                            },
                            {
                                "_key": "style",
                                "_value": "height:45vh",
                                "_type": "kv",
                                "_attrDef": "p"
                            },
                            {
                                "_key": "class",
                                "_value": [
                                    "fullWidth"
                                ],
                                "_type": "dav",
                                "_attrDef": "p"
                            },
                            {
                                "_key": "fxFlex",
                                "_value": "",
                                "_type": "kv",
                                "_attrDef": "p"
                            },
                            {
                                "_key": "fxLayoutGap",
                                "_value": "",
                                "_type": "kv",
                                "_attrDef": "p"
                            },
                            {
                                "_key": "wrap",
                                "_value": "wrap",
                                "_type": "a",
                                "_attrDef": "p"
                            },
                            {
                                "_key": "layoutAlign",
                                "_value": "center",
                                "_type": "a",
                                "_attrDef": "p"
                            },
                            {
                                "_key": "pLayoutAlign",
                                "_value": "center",
                                "_type": "a",
                                "_attrDef": "p"
                            },
                            {
                                "_key": "[fxShow]",
                                "_value": "true",
                                "_type": "kv",
                                "_attrDef": "p"
                            }
                        ],
                        "a1f29496-1952-b821-77a2-4c01ba3cc9b1": {
                            "paletteKey": "FlexLayoutCol",
                            "parentEditorKey": "c5b016dc-adfe-e1f0-763d-9498594b000a",
                            "commentid": null,
                            "designerReference": [
                                {
                                    "_key": "componentLabel",
                                    "_value": "Column",
                                    "_type": "kv",
                                    "_attrDef": "p",
                                    "_useAsLabel": true
                                },
                                {
                                    "_key": "style",
                                    "_value": "",
                                    "_type": "kv",
                                    "_attrDef": "p"
                                },
                                {
                                    "_key": "class",
                                    "_value": [
                                        "fullWidth"
                                    ],
                                    "_type": "dav",
                                    "_attrDef": "p"
                                },
                                {
                                    "_key": "fxFlex",
                                    "_value": "",
                                    "_type": "kv",
                                    "_attrDef": "p"
                                },
                                {
                                    "_key": "fxLayoutGap",
                                    "_value": "",
                                    "_type": "kv",
                                    "_attrDef": "p"
                                },
                                {
                                    "_key": "wrap",
                                    "_value": "wrap",
                                    "_type": "a",
                                    "_attrDef": "p"
                                },
                                {
                                    "_key": "layoutAlign",
                                    "_value": "center",
                                    "_type": "a",
                                    "_attrDef": "p"
                                },
                                {
                                    "_key": "pLayoutAlign",
                                    "_value": "center",
                                    "_type": "a",
                                    "_attrDef": "p"
                                },
                                {
                                    "_key": "[fxShow]",
                                    "_value": "true",
                                    "_type": "kv",
                                    "_attrDef": "p"
                                }
                            ],
                            "448d6600-c67b-0669-d356-3302e9d05b2c": {
                                "paletteKey": "Html5",
                                "parentEditorKey": "a1f29496-1952-b821-77a2-4c01ba3cc9b1",
                                "isAdvancedComponent": true,
                                "commentid": null,
                                "designerReference": [
                                    {
                                        "_key": "style",
                                        "_value": "",
                                        "_type": "kv",
                                        "_attrDef": "p"
                                    },
                                    {
                                        "_key": "class",
                                        "_value": [
                                            "fontSize2em"
                                        ],
                                        "_type": "dav",
                                        "_attrDef": "p"
                                    },
                                    {
                                        "_key": "htmlElement",
                                        "_value": "p",
                                        "_type": "dav",
                                        "_attrDef": "p",
                                        "_useAsLabel": true
                                    },
                                    {
                                        "_key": "tagType",
                                        "_value": "p",
                                        "_type": "a",
                                        "_attrDef": "p",
                                        "_visibility": false
                                    },
                                    {
                                        "_key": "name",
                                        "_value": "",
                                        "_type": "kv",
                                        "_attrDef": "p",
                                        "_visibility": false
                                    },
                                    {
                                        "_key": "sandbox",
                                        "_value": "",
                                        "_type": "kv",
                                        "_attrDef": "p",
                                        "_visibility": false
                                    },
                                    {
                                        "_key": "src",
                                        "_value": "",
                                        "_type": "kv",
                                        "_attrDef": "p",
                                        "_visibility": false
                                    },
                                    {
                                        "_key": "srcdoc",
                                        "_value": "",
                                        "_type": "kv",
                                        "_attrDef": "p",
                                        "_visibility": false
                                    },
                                    {
                                        "_key": "width",
                                        "_value": "",
                                        "_type": "kv",
                                        "_attrDef": "p",
                                        "_visibility": false
                                    },
                                    {
                                        "_key": "[autoplay]",
                                        "_value": "",
                                        "_type": "kv",
                                        "_attrDef": "p",
                                        "_visibility": false
                                    },
                                    {
                                        "_key": "[loop]",
                                        "_value": "",
                                        "_type": "kv",
                                        "_attrDef": "p",
                                        "_visibility": false
                                    },
                                    {
                                        "_key": "data",
                                        "_value": "",
                                        "_type": "kv",
                                        "_attrDef": "p",
                                        "_visibility": false
                                    },
                                    {
                                        "_key": "audioSource",
                                        "_value": [],
                                        "_type": "a",
                                        "_attrDef": "p",
                                        "_visibility": false
                                    },
                                    {
                                        "_key": "videoSource",
                                        "_value": [],
                                        "_type": "a",
                                        "_attrDef": "p",
                                        "_visibility": false
                                    },
                                    {
                                        "_key": "audioDatasource",
                                        "_value": "",
                                        "_type": "a",
                                        "_attrDef": "p",
                                        "_visibility": false
                                    },
                                    {
                                        "_key": "audioSrc",
                                        "_value": "",
                                        "_type": "a",
                                        "_attrDef": "p",
                                        "_visibility": false
                                    },
                                    {
                                        "_key": "audioType",
                                        "_value": "",
                                        "_type": "a",
                                        "_attrDef": "p",
                                        "_visibility": false
                                    },
                                    {
                                        "_key": "videoDatasource",
                                        "_value": "",
                                        "_type": "a",
                                        "_attrDef": "p",
                                        "_visibility": false
                                    },
                                    {
                                        "_key": "videoSrc",
                                        "_value": "",
                                        "_type": "a",
                                        "_attrDef": "p",
                                        "_visibility": false
                                    },
                                    {
                                        "_key": "videoType",
                                        "_value": "",
                                        "_type": "a",
                                        "_attrDef": "p",
                                        "_visibility": false
                                    },
                                    {
                                        "_key": "(audioplay)",
                                        "_value": "",
                                        "_type": "a",
                                        "_attrDef": "p",
                                        "_visibility": false
                                    },
                                    {
                                        "_key": "(videoplay)",
                                        "_value": "",
                                        "_type": "a",
                                        "_attrDef": "p",
                                        "_visibility": false
                                    },
                                    {
                                        "_key": "(audiopause)",
                                        "_value": "",
                                        "_type": "kv",
                                        "_attrDef": "p",
                                        "_visibility": false
                                    },
                                    {
                                        "_key": "(videopause)",
                                        "_value": "",
                                        "_type": "kv",
                                        "_attrDef": "p",
                                        "_visibility": false
                                    },
                                    {
                                        "_key": "(audioended)",
                                        "_value": "",
                                        "_type": "kv",
                                        "_attrDef": "p",
                                        "_visibility": false
                                    },
                                    {
                                        "_key": "(videoended)",
                                        "_value": "",
                                        "_type": "kv",
                                        "_attrDef": "p",
                                        "_visibility": false
                                    }
                                ],
                                "1ac8d9a5-35d5-1416-4712-4e964dfb1ff6": {
                                    "paletteKey": "html-editor",
                                    "parentEditorKey": "448d6600-c67b-0669-d356-3302e9d05b2c",
                                    "isAdvancedChildComponent": true,
                                    "commentid": null,
                                    "designerReference": [
                                        {
                                            "_key": "style",
                                            "_value": "",
                                            "_type": "kv",
                                            "_attrDef": "p"
                                        },
                                        {
                                            "_key": "class",
                                            "_value": "",
                                            "_type": "dav",
                                            "_attrDef": "p"
                                        },
                                        {
                                            "_key": "html",
                                            "_value": "Search By Category",
                                            "_type": "a",
                                            "_attrDef": "p"
                                        }
                                    ]
                                }
                            },
                            "0c19a335-1b90-03e2-bb47-b8793c320d14": {
                                "paletteKey": "NG-Form",
                                "parentEditorKey": "a1f29496-1952-b821-77a2-4c01ba3cc9b1",
                                "commentid": null,
                                "designerReference": [
                                    {
                                        "_key": "componentLabel",
                                        "_value": "Form",
                                        "_type": "kv",
                                        "_attrDef": "p",
                                        "_useAsLabel": true
                                    },
                                    {
                                        "_key": "style",
                                        "_value": "",
                                        "_type": "kv",
                                        "_attrDef": "p"
                                    },
                                    {
                                        "_key": "class",
                                        "_value": [
                                            "fullWidth"
                                        ],
                                        "_type": "dav",
                                        "_attrDef": "p"
                                    },
                                    {
                                        "_key": "action",
                                        "_value": "",
                                        "_type": "kv",
                                        "_attrDef": "p"
                                    },
                                    {
                                        "_key": "method",
                                        "_value": "",
                                        "_type": "kv",
                                        "_attrDef": "p"
                                    },
                                    {
                                        "_key": "target",
                                        "_value": "",
                                        "_type": "kv",
                                        "_attrDef": "p"
                                    },
                                    {
                                        "_key": "(ngSubmit)",
                                        "_value": "",
                                        "_type": "kv",
                                        "_attrDef": "p"
                                    },
                                    {
                                        "_key": "(reset)",
                                        "_value": "",
                                        "_type": "kv",
                                        "_attrDef": "p"
                                    }
                                ],
                                "a3007c4b-4e7f-f0ad-3282-dec3b097b489": {
                                    "paletteKey": "FlexLayoutRow",
                                    "parentEditorKey": "0c19a335-1b90-03e2-bb47-b8793c320d14",
                                    "commentid": null,
                                    "designerReference": [
                                        {
                                            "_key": "componentLabel",
                                            "_value": "Row",
                                            "_type": "kv",
                                            "_attrDef": "p",
                                            "_useAsLabel": true
                                        },
                                        {
                                            "_key": "style",
                                            "_value": "width:100%",
                                            "_type": "kv",
                                            "_attrDef": "p"
                                        },
                                        {
                                            "_key": "class",
                                            "_value": "",
                                            "_type": "dav",
                                            "_attrDef": "p"
                                        },
                                        {
                                            "_key": "fxFlex",
                                            "_value": "",
                                            "_type": "kv",
                                            "_attrDef": "p"
                                        },
                                        {
                                            "_key": "fxLayoutGap",
                                            "_value": "",
                                            "_type": "kv",
                                            "_attrDef": "p"
                                        },
                                        {
                                            "_key": "wrap",
                                            "_value": "wrap",
                                            "_type": "a",
                                            "_attrDef": "p"
                                        },
                                        {
                                            "_key": "layoutAlign",
                                            "_value": "center",
                                            "_type": "a",
                                            "_attrDef": "p"
                                        },
                                        {
                                            "_key": "pLayoutAlign",
                                            "_value": "center",
                                            "_type": "a",
                                            "_attrDef": "p"
                                        },
                                        {
                                            "_key": "[fxShow]",
                                            "_value": "true",
                                            "_type": "kv",
                                            "_attrDef": "p"
                                        }
                                    ],
                                    "f4a7843d-10a1-f849-7fa7-f584ad0f7f2d": {
                                        "paletteKey": "NG-Select",
                                        "parentEditorKey": "a3007c4b-4e7f-f0ad-3282-dec3b097b489",
                                        "isAdvancedComponent": true,
                                        "isCommented": "false",
                                        "commentid": null,
                                        "designerReference": [
                                            {
                                                "_key": "style",
                                                "_value": "",
                                                "_type": "kv",
                                                "_attrDef": "p"
                                            },
                                            {
                                                "_key": "class",
                                                "_value": "",
                                                "_type": "dav",
                                                "_attrDef": "p"
                                            },
                                            {
                                                "_key": "placeholder",
                                                "_value": "",
                                                "_type": "kv",
                                                "_attrDef": "p",
                                                "_useAsLabel": true
                                            },
                                            {
                                                "_key": "datasource",
                                                "_value": "",
                                                "_type": "a",
                                                "_attrDef": "p"
                                            },
                                            {
                                                "_key": "[groupOptions]",
                                                "_value": "noGroup",
                                                "_type": "dav",
                                                "_attrDef": "p"
                                            },
                                            {
                                                "_key": "[groupLabels]",
                                                "_value": "",
                                                "_type": "kv",
                                                "_attrDef": "p",
                                                "_visibility": false
                                            },
                                            {
                                                "_key": "[disableGroup]",
                                                "_value": "",
                                                "_type": "kv",
                                                "_attrDef": "p",
                                                "_visibility": false
                                            },
                                            {
                                                "_key": "[optionDatasource]",
                                                "_value": "",
                                                "_type": "a",
                                                "_attrDef": "p",
                                                "_visibility": false
                                            },
                                            {
                                                "_key": "optionValue",
                                                "_value": "",
                                                "_type": "a",
                                                "_attrDef": "p"
                                            },
                                            {
                                                "_key": "optionView",
                                                "_value": "",
                                                "_type": "a",
                                                "_attrDef": "p"
                                            },
                                            {
                                                "_key": "formControlName",
                                                "_value": "",
                                                "_type": "kv",
                                                "_attrDef": "p"
                                            },
                                            {
                                                "_key": "[(ngModel)]",
                                                "_value": "",
                                                "_type": "kv",
                                                "_attrDef": "p"
                                            },
                                            {
                                                "_key": "[(value)]",
                                                "_value": "",
                                                "_type": "kv",
                                                "_attrDef": "p"
                                            },
                                            {
                                                "_key": "[required]",
                                                "_value": "false",
                                                "_type": "kv",
                                                "_attrDef": "p"
                                            },
                                            {
                                                "_key": "[appearance]",
                                                "_value": "'outline'",
                                                "_type": "a",
                                                "_attrDef": "p"
                                            },
                                            {
                                                "_key": "[floatLabel]",
                                                "_value": "'auto'",
                                                "_type": "kv",
                                                "_attrDef": "p"
                                            },
                                            {
                                                "_key": "[disableRipple]",
                                                "_value": "",
                                                "_type": "kv",
                                                "_attrDef": "p"
                                            },
                                            {
                                                "_key": "multiple",
                                                "_value": "",
                                                "_type": "dav",
                                                "_attrDef": "p"
                                            },
                                            {
                                                "_key": "CustomTriggerValue",
                                                "_value": "",
                                                "_type": "a",
                                                "_attrDef": "p",
                                                "_visibility": false
                                            },
                                            {
                                                "_key": "(openedChange)",
                                                "_value": "",
                                                "_type": "kv",
                                                "_attrDef": "p"
                                            },
                                            {
                                                "_key": "(selectionChange)",
                                                "_value": "",
                                                "_type": "kv",
                                                "_attrDef": "p"
                                            },
                                            {
                                                "_key": "selectCustomOption",
                                                "_value": [],
                                                "_type": "a",
                                                "_attrDef": "p"
                                            },
                                            {
                                                "_key": "selectStyle",
                                                "_value": "Basic",
                                                "_type": "a",
                                                "_attrDef": "p"
                                            },
                                            {
                                                "_key": "panelClass",
                                                "_value": "",
                                                "_type": "dav",
                                                "_attrDef": "p"
                                            },
                                            {
                                                "_key": "[disabled]",
                                                "_value": "",
                                                "_type": "kv",
                                                "_attrDef": "p"
                                            },
                                            {
                                                "_key": "[errorStateMatcher]",
                                                "_value": "",
                                                "_type": "kv",
                                                "_attrDef": "p"
                                            },
                                            {
                                                "_key": "option",
                                                "_value": "option",
                                                "_type": "a",
                                                "_attrDef": "p",
                                                "_visibility": false
                                            },
                                            {
                                                "_key": "matError",
                                                "_value": [],
                                                "_type": "a",
                                                "_attrDef": "p",
                                                "_visibility": true
                                            },
                                            {
                                                "_key": "(click)",
                                                "_value": "findCategory(search.value)",
                                                "_type": "kv",
                                                "_attrDef": "c",
                                                "objValue": {
                                                    "nodeID": "sd_jii6SjVAtzvgiPym",
                                                    "functionName": "findCategory",
                                                    "activeTree": "pages",
                                                    "z": "sd_WR6iyBIOiJbrUCez",
                                                    "input": [
                                                        "search.value"
                                                    ]
                                                }
                                            },
                                            {
                                                "_key": "#search",
                                                "_value": "#search",
                                                "_type": "a",
                                                "_attrDef": "c"
                                            }
                                        ]
                                    },
                                    "25be4512-f8ce-c83b-6865-4cae3b1e19de": {
                                        "paletteKey": "NG-Input",
                                        "parentEditorKey": "a3007c4b-4e7f-f0ad-3282-dec3b097b489",
                                        "isAdvancedComponent": true,
                                        "isCommented": "true",
                                        "commentid": "1658437156432",
                                        "designerReference": [
                                            {
                                                "_key": "style",
                                                "_value": "",
                                                "_type": "kv",
                                                "_attrDef": "p"
                                            },
                                            {
                                                "_key": "class",
                                                "_value": "",
                                                "_type": "dav",
                                                "_attrDef": "p"
                                            },
                                            {
                                                "_key": "placeholder",
                                                "_value": "Search artists, catergories or years",
                                                "_type": "kv",
                                                "_attrDef": "p",
                                                "_useAsLabel": true
                                            },
                                            {
                                                "_key": "value",
                                                "_value": "",
                                                "_type": "kv",
                                                "_attrDef": "p"
                                            },
                                            {
                                                "_key": "[appearance]",
                                                "_value": "'outline'",
                                                "_type": "a",
                                                "_attrDef": "p"
                                            },
                                            {
                                                "_key": "[required]",
                                                "_value": "false",
                                                "_type": "kv",
                                                "_attrDef": "p"
                                            },
                                            {
                                                "_key": "[(ngModel)]",
                                                "_value": "",
                                                "_type": "kv",
                                                "_attrDef": "p",
                                                "_customAttributeFlag": "flowpicker"
                                            },
                                            {
                                                "_key": "color",
                                                "_value": "",
                                                "_type": "kv",
                                                "_attrDef": "p"
                                            },
                                            {
                                                "_key": "name",
                                                "_value": "",
                                                "_type": "kv",
                                                "_attrDef": "p"
                                            },
                                            {
                                                "_key": "type",
                                                "_value": "",
                                                "_type": "kv",
                                                "_attrDef": "p"
                                            },
                                            {
                                                "_key": "[formControl]",
                                                "_value": "",
                                                "_type": "kv",
                                                "_attrDef": "p"
                                            },
                                            {
                                                "_key": "readonly",
                                                "_value": "",
                                                "_type": "kv",
                                                "_attrDef": "p"
                                            },
                                            {
                                                "_key": "[disabled]",
                                                "_value": "",
                                                "_type": "kv",
                                                "_attrDef": "p"
                                            },
                                            {
                                                "_key": "id",
                                                "_value": "",
                                                "_type": "kv",
                                                "_attrDef": "p"
                                            },
                                            {
                                                "_key": "[floatLabel]",
                                                "_value": "'auto'",
                                                "_type": "kv",
                                                "_attrDef": "p"
                                            },
                                            {
                                                "_key": "[hideRequiredMarker]",
                                                "_value": "false",
                                                "_type": "kv",
                                                "_attrDef": "p",
                                                "_complexity": "advanced"
                                            },
                                            {
                                                "_key": "matError",
                                                "_value": [],
                                                "_type": "a",
                                                "_attrDef": "p",
                                                "_visibility": true
                                            },
                                            {
                                                "_key": "inputHint",
                                                "_value": [],
                                                "_type": "a",
                                                "_attrDef": "p",
                                                "_visibility": true
                                            },
                                            {
                                                "_key": "Label",
                                                "_value": "",
                                                "_type": "a",
                                                "_attrDef": "p",
                                                "_visibility": true
                                            },
                                            {
                                                "_key": "Suffix Icon",
                                                "_value": "search",
                                                "_type": "a",
                                                "_attrDef": "p",
                                                "_visibility": true
                                            },
                                            {
                                                "_key": "(suffixIconClick)",
                                                "_value": "findCategory(search.value)",
                                                "_type": "a",
                                                "_attrDef": "p",
                                                "_visibility": true,
                                                "_customAttributeFlag": "flowpicker",
                                                "objValue": {
                                                    "nodeID": "sd_jii6SjVAtzvgiPym",
                                                    "functionName": "findCategory",
                                                    "activeTree": "pages",
                                                    "z": "sd_WR6iyBIOiJbrUCez",
                                                    "input": [
                                                        "search.value"
                                                    ]
                                                }
                                            },
                                            {
                                                "_key": "Prefix Icon",
                                                "_value": "",
                                                "_type": "a",
                                                "_attrDef": "p",
                                                "_visibility": true
                                            },
                                            {
                                                "_key": "(prefixIconClick)",
                                                "_value": "",
                                                "_type": "a",
                                                "_attrDef": "p",
                                                "_visibility": true
                                            },
                                            {
                                                "_key": "Prefix",
                                                "_value": "",
                                                "_type": "a",
                                                "_attrDef": "p",
                                                "_visibility": true
                                            },
                                            {
                                                "_key": "Suffix",
                                                "_value": "",
                                                "_type": "a",
                                                "_attrDef": "p",
                                                "_visibility": true
                                            },
                                            {
                                                "_key": "#search",
                                                "_value": "#search",
                                                "_type": "a",
                                                "_attrDef": "c"
                                            }
                                        ]
                                    }
                                },
                                "0fb0d045-8400-87b5-37cc-cbed38753701": {
                                    "paletteKey": "ng-autocomplete",
                                    "parentEditorKey": "0c19a335-1b90-03e2-bb47-b8793c320d14",
                                    "isAdvancedComponent": true,
                                    "isCommented": "true",
                                    "commentid": "1658333076850",
                                    "designerReference": [
                                        {
                                            "_key": "componentLabel",
                                            "_value": "Autocomplete",
                                            "_type": "kv",
                                            "_attrDef": "p",
                                            "_useAsLabel": true
                                        },
                                        {
                                            "_key": "style",
                                            "_value": "",
                                            "_type": "kv",
                                            "_attrDef": "p"
                                        },
                                        {
                                            "_key": "class",
                                            "_value": "",
                                            "_type": "dav",
                                            "_attrDef": "p"
                                        },
                                        {
                                            "_key": "matAutocomplete",
                                            "_value": "auto",
                                            "_type": "vk",
                                            "_attrDef": "p"
                                        },
                                        {
                                            "_key": "autoActiveFirstOption",
                                            "_value": "",
                                            "_type": "a",
                                            "_attrDef": "p",
                                            "_complexity": "advanced"
                                        },
                                        {
                                            "_key": "[disableRipple]",
                                            "_value": "",
                                            "_type": "kv",
                                            "_attrDef": "p",
                                            "_complexity": "advanced"
                                        },
                                        {
                                            "_key": "[displayWith]",
                                            "_value": "",
                                            "_type": "kv",
                                            "_attrDef": "p",
                                            "_complexity": "advanced"
                                        },
                                        {
                                            "_key": "[panelWidth]",
                                            "_value": "",
                                            "_type": "kv",
                                            "_attrDef": "p",
                                            "_complexity": "advanced"
                                        },
                                        {
                                            "_key": "(closed)",
                                            "_value": "",
                                            "_type": "kv",
                                            "_attrDef": "p",
                                            "_complexity": "advanced"
                                        },
                                        {
                                            "_key": "(opened)",
                                            "_value": "",
                                            "_type": "kv",
                                            "_attrDef": "p",
                                            "_complexity": "advanced"
                                        },
                                        {
                                            "_key": "(optionSelected)",
                                            "_value": "",
                                            "_type": "kv",
                                            "_attrDef": "p",
                                            "_complexity": "advanced"
                                        },
                                        {
                                            "_key": "*ngFor",
                                            "_value": "let option of page.options ",
                                            "_type": "kv",
                                            "_attrDef": "p"
                                        },
                                        {
                                            "_key": "(optionClick)",
                                            "_value": "",
                                            "_type": "dav",
                                            "_attrDef": "p"
                                        },
                                        {
                                            "_key": "[groupOptions]",
                                            "_value": "noGroup",
                                            "_type": "dav",
                                            "_attrDef": "p"
                                        },
                                        {
                                            "_key": "optionView",
                                            "_value": "{{option}}",
                                            "_type": "a",
                                            "_attrDef": "p"
                                        },
                                        {
                                            "_key": "[value]",
                                            "_value": "option",
                                            "_type": "kv",
                                            "_attrDef": "p"
                                        },
                                        {
                                            "_key": "[optionDatasource]",
                                            "_value": "",
                                            "_type": "a",
                                            "_attrDef": "p",
                                            "_visibility": false
                                        },
                                        {
                                            "_key": "[label]",
                                            "_value": "",
                                            "_type": "kv",
                                            "_attrDef": "p",
                                            "_visibility": false
                                        },
                                        {
                                            "_key": "[matAutocomplete]",
                                            "_value": "auto",
                                            "_type": "kv",
                                            "_attrDef": "c"
                                        }
                                    ]
                                },
                                "6ad373d4-f686-9ab5-ec55-3e76b2b2a4ba": {
                                    "paletteKey": "NG-RaisedButton",
                                    "parentEditorKey": "0c19a335-1b90-03e2-bb47-b8793c320d14",
                                    "isCommented": "true",
                                    "commentid": "1658386576579",
                                    "designerReference": [
                                        {
                                            "_key": "style",
                                            "_value": "",
                                            "_type": "kv",
                                            "_attrDef": "p"
                                        },
                                        {
                                            "_key": "class",
                                            "_value": "",
                                            "_type": "dav",
                                            "_attrDef": "p"
                                        },
                                        {
                                            "_key": "buttonname",
                                            "_value": "Raised Button",
                                            "_type": "a",
                                            "_attrDef": "p",
                                            "_useAsLabel": true
                                        },
                                        {
                                            "_key": "color",
                                            "_value": "",
                                            "_type": "kv",
                                            "_attrDef": "p"
                                        },
                                        {
                                            "_key": "(click)",
                                            "_value": "getArtsits(search.value)",
                                            "_type": "kv",
                                            "_attrDef": "p",
                                            "objValue": {
                                                "nodeID": "sd_Gvav1Gt6vl9XDD1s",
                                                "functionName": "getArtsits",
                                                "activeTree": "pages",
                                                "z": "sd_WR6iyBIOiJbrUCez",
                                                "input": [
                                                    "search.value"
                                                ]
                                            }
                                        },
                                        {
                                            "_key": "[disabled]",
                                            "_value": "",
                                            "_type": "kv",
                                            "_attrDef": "p"
                                        },
                                        {
                                            "_key": "[disableRipple]",
                                            "_value": "",
                                            "_type": "kv",
                                            "_attrDef": "p"
                                        },
                                        {
                                            "_key": "type",
                                            "_value": "",
                                            "_type": "kv",
                                            "_attrDef": "p"
                                        },
                                        {
                                            "_key": "routerLink",
                                            "_value": "",
                                            "_type": "kv",
                                            "_attrDef": "p"
                                        }
                                    ]
                                }
                            }
                        }
                    }
                }
            }
        }
    }
}
